leapimport/__init__.py
leapimport/leapimport.py
leapimport-0.2.0.dist-info/DESCRIPTION.rst
leapimport-0.2.0.dist-info/METADATA
leapimport-0.2.0.dist-info/RECORD
leapimport-0.2.0.dist-info/WHEEL
leapimport-0.2.0.dist-info/metadata.json
leapimport-0.2.0.dist-info/top_level.txt
