Metadata-Version: 2.0
Name: leapimport
Version: 0.2.0
Summary: Simple package to import binary LeapMotion recording data.
Home-page: https://github.com/richjoyce/leapimport
Author: Richard Joyce
Author-email: rjoyce@ucdavis.edu
License: MIT license
Keywords: leapimport
Platform: UNKNOWN
Classifier: Development Status :: 2 - Pre-Alpha
Classifier: Intended Audience :: Developers
Classifier: License :: OSI Approved :: MIT License
Classifier: Natural Language :: English
Classifier: Programming Language :: Python :: 2
Classifier: Programming Language :: Python :: 2.6
Classifier: Programming Language :: Python :: 2.7
